{
  "navigation": {
    "dashboards": "Tableaux de bord",
    "crm": "GRC",
    "apps": "Apps",
    "email": "E-mail",
    "list": "Liste",
    "preview": "Aperçu",
    "edit": "Éditer",
    "add": "Ajouter",
    "rdhs": "RDHS",
    "hospital": "Hospital",
    "patient": "Patient",
    "humanResources": "Human Resources",
    "addHumanresources": "Human Resources",
    "humanResourcesRoles": "Human Resources Roles",
    "assets": "Assets",
    "assetsType": "Assets Type",
    "disease": "Disease Type",
    "view": "Voir",
    "pages": "Pages",
    "checkout": "Vérifier",
    "propertyListing": "Liste des biens",
    "createDeal": "Créer un accord",
    "basic": "basique",
    "advanced": "Avancée",
    "statistics": "Statistiques",
    "gamification": "Gamification",
    "actions": "Actions",
    "muiTables": "Tableaux MUI",
    "apex": "Sommet",
    "foundation": "fondation",
    "components": "Composants",
    "menuExamples": "Exemples de menus",
    "raiseSupport": "Augmenter le soutien",
    "others": "Les autres",
    "itemWithBadge": "Article avec badge"
  }
}
